netprotocols/__init__.py
netprotocols/base/packet.py
netprotocols/base/protocol.py
netprotocols/layer2/arp.py
netprotocols/layer2/ethernet.py
netprotocols/layer3/icmp.py
netprotocols/layer3/ip.py
netprotocols/layer4/tcp.py
netprotocols/layer4/udp.py
netprotocols/utils/__init__.py
netprotocols/utils/exceptions.py
netprotocols/utils/random_mac.py
netprotocols/utils/validation/_base.py
netprotocols/utils/validation/ipv4.py
netprotocols/utils/validation/mac.py
netprotocols-0.8.0.dist-info/WHEEL
netprotocols-0.8.0.dist-info/METADATA
netprotocols-0.8.0.dist-info/RECORD
